rdii/__init__.py
rdii/rain.py
rdii/test_rain.py
rdii-0.1.dist-info/LICENSE
rdii-0.1.dist-info/METADATA
rdii-0.1.dist-info/WHEEL
rdii-0.1.dist-info/top_level.txt
rdii-0.1.dist-info/RECORD
