Metadata-Version: 2.1
Name: rdii
Version: 0.1
Summary: Rainfall-Derived Infiltration and Inflow library
Home-page: https://github.com/klangner/rdii
Author: Krzysztof Langner
Author-email: klangner@gmail.com
License: UNKNOWN
Platform: UNKNOWN
Classifier: Programming Language :: Python :: 3
Classifier: License :: OSI Approved :: MIT License
Classifier: Operating System :: OS Independent
